setup.py
scikit_time.egg-info/PKG-INFO
scikit_time.egg-info/SOURCES.txt
scikit_time.egg-info/dependency_links.txt
scikit_time.egg-info/not-zip-safe
scikit_time.egg-info/top_level.txt
scikittime/__init__.py